hfer/__init__.py
hfer/_builder.py
hfer/_registry.py
hfer/hf_backend.py
hfer-0.0.5.dist-info/LICENSE
hfer-0.0.5.dist-info/METADATA
hfer-0.0.5.dist-info/WHEEL
hfer-0.0.5.dist-info/top_level.txt
hfer-0.0.5.dist-info/RECORD
