Metadata-Version: 2.1
Name: hfer
Version: 0.0.5
Summary: one-line hf model
Home-page: https://github.com/XuyangShen/HFer
Author: Ryan
Author-email: xuyangshen1122@gmail.com
License-File: LICENSE
